gendummy/__init__.py
gendummy/gd.py
gendummy-0.1.1.dist-info/METADATA
gendummy-0.1.1.dist-info/WHEEL
gendummy-0.1.1.dist-info/top_level.txt
gendummy-0.1.1.dist-info/RECORD
