Metadata-Version: 2.1
Name: gendummy
Version: 0.1.1
Summary: A library for generating dummy data in pandas DataFrames.
Author-email: Andrew Romanov <romanoffnv@gmail.com>
License: MIT
Requires-Python: >=3.6
Requires-Dist: pandas
Requires-Dist: numpy
Requires-Dist: openpyxl
